gym_sokoban/__init__.py
gym_sokoban/envs/__init__.py
gym_sokoban/envs/available_envs.json
gym_sokoban/envs/boxoban_env.py
gym_sokoban/envs/render_utils.py
gym_sokoban/envs/room_utils.py
gym_sokoban/envs/sokoban_env.py
gym_sokoban/envs/sokoban_env_fixed_targets.py
gym_sokoban/envs/sokoban_env_pull.py
gym_sokoban/envs/sokoban_env_two_player.py
gym_sokoban/envs/sokoban_env_variations.py
gym_sokoban/envs/surface/box.png
gym_sokoban/envs/surface/box_on_target.png
gym_sokoban/envs/surface/box_target.png
gym_sokoban/envs/surface/floor.png
gym_sokoban/envs/surface/player.png
gym_sokoban/envs/surface/player_on_target.png
gym_sokoban/envs/surface/wall.png
gym_sokoban/envs/surface/multibox/box0.png
gym_sokoban/envs/surface/multibox/box0_on_target.png
gym_sokoban/envs/surface/multibox/box0_on_wrong_target.png
gym_sokoban/envs/surface/multibox/box0_target.png
gym_sokoban/envs/surface/multibox/box1.png
gym_sokoban/envs/surface/multibox/box1_on_target.png
gym_sokoban/envs/surface/multibox/box1_on_wrong_target.png
gym_sokoban/envs/surface/multibox/box1_target.png
gym_sokoban/envs/surface/multibox/box2.png
gym_sokoban/envs/surface/multibox/box2_on_target.png
gym_sokoban/envs/surface/multibox/box2_on_wrong_target.png
gym_sokoban/envs/surface/multibox/box2_target.png
gym_sokoban/envs/surface/multibox/box3.png
gym_sokoban/envs/surface/multibox/box3_on_target.png
gym_sokoban/envs/surface/multibox/box3_on_wrong_target.png
gym_sokoban/envs/surface/multibox/box3_target.png
gym_sokoban/envs/surface/multiplayer/player0.png
gym_sokoban/envs/surface/multiplayer/player0_on_target.png
gym_sokoban/envs/surface/multiplayer/player1.png
gym_sokoban/envs/surface/multiplayer/player1_on_target.png
gym_sokoban/envs/surface/tiny_world/box.png
gym_sokoban/envs/surface/tiny_world/box_on_target.png
gym_sokoban/envs/surface/tiny_world/box_target.png
gym_sokoban/envs/surface/tiny_world/floor.png
gym_sokoban/envs/surface/tiny_world/player.png
gym_sokoban/envs/surface/tiny_world/player_on_target.png
gym_sokoban-0.0.6.dist-info/LICENSE
gym_sokoban-0.0.6.dist-info/METADATA
gym_sokoban-0.0.6.dist-info/WHEEL
gym_sokoban-0.0.6.dist-info/top_level.txt
gym_sokoban-0.0.6.dist-info/RECORD
