Metadata-Version: 2.1
Name: gym-sokoban
Version: 0.0.6
Summary: Sokoban environment for OpenAI Gym
Home-page: https://github.com/mpSchrader/gym-sokoban
Author: Max-Philipp Schrader
License: UNKNOWN
Platform: UNKNOWN
Classifier: Programming Language :: Python :: 3
Classifier: License :: OSI Approved :: MIT License
Classifier: Operating System :: OS Independent
Requires-Dist: gym (>=0.2.3)
Requires-Dist: numpy (>=1.14.1)
Requires-Dist: tqdm (>=4.32.1)
Requires-Dist: imageio (>=2.3.0)
Requires-Dist: requests (>=2.22.0)
